notejob/__init__.py
notejob/center/README.md
notejob/center/__init__.py
notejob/center/conf.ini
notejob/center/config.py
notejob/center/configs.py
notejob/center/docker-compose.yml
notejob/center/docker_gun.py
notejob/center/docker_start.sh
notejob/center/gun.py
notejob/center/manage.py
notejob/center/requirements.txt
notejob/center/scheduler.lock
notejob/center/start.sh
notejob/center/app/__init__.py
notejob/center/app/decorated.py
notejob/center/app/api/__init__.py
notejob/center/app/api/core.py
notejob/center/app/api/views.py
notejob/center/app/common/__init__.py
notejob/center/app/common/functions.py
notejob/center/app/crons/__init__.py
notejob/center/app/crons/core.py
notejob/center/app/main/__init__.py
notejob/center/app/main/core.py
notejob/center/app/main/errors.py
notejob/center/app/main/views.py
notejob/center/app/scheduler/CuBackgroundScheduler.py
notejob/center/app/scheduler/CuGeventScheduler.py
notejob/center/app/scheduler/__init__.py
notejob/center/app/static/__init__.py
notejob/center/app/static/jquery.js
notejob/center/app/static/vue.js
notejob/center/app/static/images/__init__.py
notejob/center/app/static/images/mini_code.png
notejob/center/app/static/js/__init__.py
notejob/center/app/static/js/ajaxForm.js
notejob/center/app/static/js/common.js
notejob/center/app/static/js/jquery.js
notejob/center/app/static/js/md5.js
notejob/center/app/static/js/qrcode.min.js
notejob/center/app/static/js/requests.js
notejob/center/app/static/js/signs.js
notejob/center/app/static/js/wind.js
notejob/center/app/static/js/artDialog/__init__.py
notejob/center/app/static/js/artDialog/artDialog.extend.js
notejob/center/app/static/js/artDialog/artDialog.js
notejob/center/app/static/js/artDialog/iframeTools.js
notejob/center/app/static/js/artDialog/skins/__init__.py
notejob/center/app/static/js/artDialog/skins/blue.css
notejob/center/app/static/js/artDialog/skins/default.css
notejob/center/app/static/js/artDialog/skins/blue/__init__.py
notejob-0.2.23.dist-info/LICENSE
notejob-0.2.23.dist-info/METADATA
notejob-0.2.23.dist-info/WHEEL
notejob-0.2.23.dist-info/top_level.txt
notejob-0.2.23.dist-info/RECORD
