Metadata-Version: 2.1
Name: notejob
Version: 0.2.23
Summary: notejob
Home-page: https://github.com/1007530194
Author: niuliangtao
Author-email: 1007530194@qq.com
License: UNKNOWN
Platform: UNKNOWN
Requires-Dist: apscheduler
Requires-Dist: gunicorn
Requires-Dist: flask-migrate
Requires-Dist: flask-script
